{"cameraMode":{"drawMode":0,"name":"Shaded","section":"Shading Mode"},"sceneLighting":true,"audioPlay":false,"sceneViewState":{"m_AlwaysRefresh":false,"showFog":true,"showSkybox":true,"showFlares":true,"showImageEffects":true,"showParticleSystems":true,"showVisualEffectGraphs":true,"m_FxEnabled":true},"in2DMode":false,"pivot":{"x":15.019238471984864,"y":1.1119308471679688,"z":-5.244754791259766},"rotation":{"x":0.009442181326448918,"y":0.8747659921646118,"z":-0.4841529428958893,"w":0.01706010103225708},"size":7.953030586242676,"orthographic":false}